VivadoProjects/rtl/VGA_Sync_Handler.v
// Based on documentation fromDavid J. Marion in reference to:
// 
// Chu, Pong P.
// Wiley, 2008
// "FPGA Prototyping by Verilog Examples: Xilinx Spartan-3 Version" 
//
// Based on an FPGA with 100MHz clock
//
// VGA Specs:
// 640x480 pixel resolution at 60 Hz
// Based on VGA standards, we need "extra" resolution outside visible area (porches). This gives:
// 800 pixels/line and 525 lines/screen @60Hz ==> 800*525*60 = ~25M pixels/second
//
// This means we will need a 25 MHz signal to run the VGA protocol (need to generate horizontal sync, vertical sync, 
// pixel signal, and a display on signal)


module vga_handler(
    i_clock,
    i_reset,
    o_display_on,
    o_hsync,
    o_vsync,
    o_pixel_clock,
    o_h_spot,
    o_v_spot
);

input i_clock;          //100 MHz from Artix-7
input i_reset;          // to reset system
output o_display_on;     // this is high when we are rastering within the visible display area (640x480 area)
output o_hsync;         // horizontal sync (signals when a line is finished)
output o_vsync;         // vertical sync (signals when last line on screen is finished)
output o_pixel_clock;   // 25MHz signal for controlling pixel/second display rate
output [9:0] o_h_spot;  // counter for keeping track of what pixel we are on horizontally      
output [9:0] o_v_spot;  // counter for keeping track of what pixel we are on vertically

// We now will lay out the values we will use for sectioning the total pixel area into the visible, and 
// various non-visible sections as described by the VGA standard (Included in this folder is a schematic from
// electronics stack exchange that shows the various areas outlined in the VGA standards)

//horizontal
parameter horz_dis_area = 640;      //width of horizontal display area in pixels
parameter horz_front = 48;          // horizontal front porch width in pixels
parameter horz_back = 16;           // horizontal back porch width in pixels
parameter horz_retrace = 96;        // horizontal retrace area width in pixels
parameter horz_max = (horz_dis_area + horz_front + horz_back + horz_retrace) - 1; //max number for horz_counter
                                                                                  // horz_max = 799 pixels
//vertical (all variables descriptions are same, just for vertical)
parameter vert_dis_area = 480;      
parameter vert_front = 10;          
parameter vert_back = 33;           
parameter vert_retrace = 2;        
parameter vert_max = (vert_dis_area + vert_front + vert_back + vert_retrace) - 1; //max number for horz_counter
                                                                                  // vert_max = 524 pixels

// We now will generate the 25MHz signal we will use to drive our pixel tick and increment our counters with:
      
reg [1:0] quarter_counter = 2'b00; //2 bit number that wraps every 4 increments 00,01,10,11 --> 00, . . . 

always @ (posedge i_clock)
    begin
    if(i_reset)
        quarter_counter <= 0;
    else
        quarter_counter <= quarter_counter + 1; //increment quarter counter
    end

//essentially, because quarter counter only has 2 values (2-bit binary number) we can check for one of these 
//values to be true to give us a high signal (logical true) 1/4 of the time. Therefore if we are incrementing
//quarter_counter at a rate of 100MHz with this logic, we will get a 100MHz/4 or 25MHz signal!
wire c_25MHz = (quarter_counter == 0) ? 1 : 0; //clock output (wire so that it globally updates immediately -- not registered)
assign o_pixel_clock = c_25MHz; 

// We will now move on to the generation of the syncing and pixel location signals:
// We make two temporary registers for each sync signal to cut down on any metastability issues and visual bugs:

// counters for pixel locations (two for each to ripple for stability):
reg [9:0] h_count_pre;
reg [9:0] h_count_post;
reg [9:0] v_count_pre;
reg [9:0] v_count_post;

//  syncing signal (two for each to ripple for stability):
wire h_sync_pre;
wire v_sync_pre;
reg h_sync_post;
reg v_sync_post;

//Ripple the registers (both counters and sync signals)
always @ (posedge i_clock)
    if(i_reset)
    begin
        h_count_pre <= 0;
        v_count_pre <= 0;
        h_sync_post <= 1'b0;
        v_sync_post <= 1'b0;
    end
    else begin
        h_count_post <= h_count_pre;
        v_count_post <= v_count_pre;
        h_sync_post <= h_sync_pre;
        v_sync_post <= v_sync_pre;
    end

// Now we can actually do the counter logic to generate the signals we need:
//
// For Horizontal pixel count:
always @ (posedge i_clock)       //running on the 100MHz clock to not cause clock domain issues
    begin
    if(i_reset) begin
        h_count_pre <= 0;
    end
    else if(c_25MHz)begin
            if(h_count_post == horz_max)                //This is when we reach the end of a line!
                h_count_pre <= 0;                       
            else
                h_count_pre <= h_count_post +1;         // If not at the end of line, just increase count
            end
    end

// For vertical counter:

always @ (posedge i_clock)
    begin
        if(i_reset)begin
            v_count_pre <= 0;
        end
        else if(c_25MHz) begin
                if(h_count_post == horz_max)
                begin
                    if(v_count_post == vert_max)
                        v_count_pre <= 0;
                    else
                        v_count_pre <= v_count_post + 1;
                end
        end
    end

// We can now generate the sync pulses (we want these to be high during retrace and low everywhere else)

// horizontal sync pulse:

// we make this low when we are both:
// 1) Past the visible display area and porch
// 2) Before the end of the retrace width
assign h_sync_pre = (h_count_post >= (horz_dis_area + horz_back) && h_count_post <= (horz_dis_area + horz_back + horz_retrace - 1));

// We do the same for the vertical sync pulse:

assign v_sync_pre = (v_count_post >= (vert_dis_area + vert_back) && v_count_post <= (vert_dis_area + vert_back + vert_retrace - 1));

// And now we set the display_on signal high when we are both:
// 1) within the horizontal display area
// 2) within the vertical display area

assign o_display_on = ((h_count_post < horz_dis_area) && (v_count_post < vert_dis_area)); //1 when in dis. area 0 outside of it

//Now we just assign all of our outputs from the rippled values:

assign o_hsync = h_sync_post;
assign o_vsync = v_sync_post;
assign o_h_spot = h_count_post;
assign o_v_spot = v_count_post;
assign o_pixel_clock = c_25MHz;

endmodule

VGA_Sync_HandlerTB.v
`timescale 1ns / 1ps
`include "VGA_Sync_Handler.v"

module  VGA_Sync_HandlerTB;

//define signals from test bench

reg tb_clock = 1'b0;
reg tb_reset = 1'b1;

wire tb_display_on;
wire tb_hsync;
wire tb_vsync;
wire tb_pixel_clock;
wire [9:0] tb_h_spot;
wire [9:0] tb_v_spot;

vga_handler UUT
(
    .i_clock(tb_clock),
    .i_reset(tb_reset),
    .o_display_on(tb_display_on),
    .o_hsync(tb_hsync),
    .o_vsync(tb_vsync),
    .o_pixel_clock(tb_pixel_clock),
    .o_h_spot(tb_h_spot),
    .o_v_spot(tb_v_spot)
);

initial begin
    $dumpfile("VGA_Sync_HandlerTB.vcd"); //dump file name
    $dumpvars(0, VGA_Sync_HandlerTB);  //dumps all signals in test bench
end

// Here we are generating a 100kHz clock signal. We can do this by using # to pause for the
// correct number of loops so that our period we are using to define tb_clock is equal to the period
// of a 100kHz clock --> 100kHz = 1/100,000 seconds = 0.00001 seconds or 10us. it takes 2 toggles for 
//a complete period so we divide the waitcount by 2. This means we need to wait for 10 us so we use #5000

always #5 tb_clock <= !tb_clock;  //toggle the value from 0 -> 1 -> 0 -> ... makes square wave => Clock signal!

// run code that we run only once to set up test environment. This is why we use "initial"
initial begin

    $display("Testing VGA_Handler");

    tb_reset <= 1'b0;
    #200000
    tb_reset <= 1'b1;

    $display("Test Complete");  //to make sure test finishes!
    $finish;

end

endmodule

VGA_Sync_HandlerTB.vcd
$date
	Fri May 30 02:51:19 2025
$end
$version
	Icarus Verilog
$end
$timescale
	1ps
$end
$scope module VGA_Sync_HandlerTB $end
$var wire 1 ! tb_vsync $end
$var wire 10 " tb_v_spot [9:0] $end
$var wire 1 # tb_pixel_clock $end
$var wire 1 $ tb_hsync $end
$var wire 10 % tb_h_spot [9:0] $end
$var wire 1 & tb_display_on $end
$var reg 1 ' tb_clock $end
$var reg 1 ( tb_reset $end
$scope module UUT $end
$var wire 1 ) h_sync_pre $end
$var wire 1 ' i_clock $end
$var wire 1 ( i_reset $end
$var wire 1 & o_display_on $end
$var wire 10 * o_h_spot [9:0] $end
$var wire 1 $ o_hsync $end
$var wire 1 # o_pixel_clock $end
$var wire 10 + o_v_spot [9:0] $end
$var wire 1 ! o_vsync $end
$var wire 1 , v_sync_pre $end
$var wire 1 - c_25MHz $end
$var parameter 32 . horz_back $end
$var parameter 32 / horz_dis_area $end
$var parameter 32 0 horz_front $end
$var parameter 36 1 horz_max $end
$var parameter 32 2 horz_retrace $end
$var parameter 32 3 vert_back $end
$var parameter 32 4 vert_dis_area $end
$var parameter 32 5 vert_front $end
$var parameter 36 6 vert_max $end
$var parameter 32 7 vert_retrace $end
$var reg 10 8 h_count_post [9:0] $end
$var reg 10 9 h_count_pre [9:0] $end
$var reg 1 : h_sync_post $end
$var reg 2 ; quarter_counter [1:0] $end
$var reg 10 < v_count_post [9:0] $end
$var reg 10 = v_count_pre [9:0] $end
$var reg 1 > v_sync_post $end
$upscope $end
$upscope $end
$enddefinitions $end
$comment Show the parameter values. $end
$dumpall
b10 7
b1000001100 6
b1010 5
b111100000 4
b100001 3
b1100000 2
b1100011111 1
b110000 0
b1010000000 /
b10000 .
$end
#0
$dumpvars
0>
b0 =
bx <
b0 ;
0:
b0 9
bx 8
1-
x,
bx +
bx *
x)
0(
0'
x&
bx %
0$
1#
bx "
0!
$end
#5000
0#
0-
0,
0)
1&
x!
x>
x$
x:
b0 "
b0 +
b0 <
b0 %
b0 *
b0 8
b1 ;
1'
#10000
0'
#15000
b10 ;
0!
0>
0$
0:
1'
#20000
0'
#25000
b11 ;
1'
#30000
0'
#35000
b1 9
1#
1-
b0 ;
1'
#40000
0'
#45000
0#
0-
b1 %
b1 *
b1 8
b1 ;
1'
#50000
0'
#55000
b10 ;
1'
#60000
0'
#65000
b11 ;
1'
#70000
0'
#75000
b10 9
1#
1-
b0 ;
1'
#80000
0'
#85000
0#
0-
b10 %
b10 *
b10 8
b1 ;
1'
#90000
0'
#95000
b10 ;
1'
#100000
0'
#105000
b11 ;
1'
#110000
0'
#115000
b11 9
1#
1-
b0 ;
1'
#120000
0'
#125000
0#
0-
b11 %
b11 *
b11 8
b1 ;
1'
#130000
0'
#135000
b10 ;
1'
#140000
0'
#145000
b11 ;
1'
#150000
0'
#155000
b100 9
1#
1-
b0 ;
1'
#160000
0'
#165000
0#
0-
b100 %
b100 *
b100 8
b1 ;
1'
#170000
0'
#175000
b10 ;
1'
#180000
0'
#185000
b11 ;
1'
#190000
0'
#195000
b101 9
1#
1-
b0 ;
1'
#200000
0'
#205000
0#
0-
b101 %
b101 *
b101 8
b1 ;
1'
#210000
0'
#215000
b10 ;
1'
#220000
0'
#225000
b11 ;
1'
#230000
0'
#235000
b110 9
1#
1-
b0 ;
1'
#240000
0'
#245000
0#
0-
b110 %
b110 *
b110 8
b1 ;
1'
#250000
0'
#255000
b10 ;
1'
#260000
0'
#265000
b11 ;
1'
#270000
0'
#275000
b111 9
1#
1-
b0 ;
1'
#280000
0'
#285000
0#
0-
b111 %
b111 *
b111 8
b1 ;
1'
#290000
0'
#295000
b10 ;
1'
#300000
0'
#305000
b11 ;
1'
#310000
0'
#315000
b1000 9
1#
1-
b0 ;
1'
#320000
0'
#325000
0#
0-
b1000 %
b1000 *
b1000 8
b1 ;
1'
#330000
0'
#335000
b10 ;
1'
#340000
0'
#345000
b11 ;
1'
#350000
0'
#355000
b1001 9
1#
1-
b0 ;
1'
#360000
0'
#365000
0#
0-
b1001 %
b1001 *
b1001 8
b1 ;
1'
#370000
0'
#375000
b10 ;
1'
#380000
0'
#385000
b11 ;
1'
#390000
0'
#395000
b1010 9
1#
1-
b0 ;
1'
#400000
0'
#405000
0#
0-
b1010 %
b1010 *
b1010 8
b1 ;
1'
#410000
0'
#415000
b10 ;
1'
#420000
0'
#425000
b11 ;
1'
#430000
0'
#435000
b1011 9
1#
1-
b0 ;
1'
#440000
0'
#445000
0#
0-
b1011 %
b1011 *
b1011 8
b1 ;
1'
#450000
0'
#455000
b10 ;
1'
#460000
0'
#465000
b11 ;
1'
#470000
0'
#475000
b1100 9
1#
1-
b0 ;
1'
#480000
0'
#485000
0#
0-
b1100 %
b1100 *
b1100 8
b1 ;
1'
#490000
0'
#495000
b10 ;
1'
#500000
0'
#505000
b11 ;
1'
#510000
0'
#515000
b1101 9
1#
1-
b0 ;
1'
#520000
0'
#525000
0#
0-
b1101 %
b1101 *
b1101 8
b1 ;
1'
#530000
0'
#535000
b10 ;
1'
#540000
0'
#545000
b11 ;
1'
#550000
0'
#555000
b1110 9
1#
1-
b0 ;
1'
#560000
0'
#565000
0#
0-
b1110 %
b1110 *
b1110 8
b1 ;
1'
#570000
0'
#575000
b10 ;
1'
#580000
0'
#585000
b11 ;
1'
#590000
0'
#595000
b1111 9
1#
1-
b0 ;
1'
#600000
0'
#605000
0#
0-
b1111 %
b1111 *
b1111 8
b1 ;
1'
#610000
0'
#615000
b10 ;
1'
#620000
0'
#625000
b11 ;
1'
#630000
0'
#635000
b10000 9
1#
1-
b0 ;
1'
#640000
0'
#645000
0#
0-
b10000 %
b10000 *
b10000 8
b1 ;
1'
#650000
0'
#655000
b10 ;
1'
#660000
0'
#665000
b11 ;
1'
#670000
0'
#675000
b10001 9
1#
1-
b0 ;
1'
#680000
0'
#685000
0#
0-
b10001 %
b10001 *
b10001 8
b1 ;
1'
#690000
0'
#695000
b10 ;
1'
#700000
0'
#705000
b11 ;
1'
#710000
0'
#715000
b10010 9
1#
1-
b0 ;
1'
#720000
0'
#725000
0#
0-
b10010 %
b10010 *
b10010 8
b1 ;
1'
#730000
0'
#735000
b10 ;
1'
#740000
0'
#745000
b11 ;
1'
#750000
0'
#755000
b10011 9
1#
1-
b0 ;
1'
#760000
0'
#765000
0#
0-
b10011 %
b10011 *
b10011 8
b1 ;
1'
#770000
0'
#775000
b10 ;
1'
#780000
0'
#785000
b11 ;
1'
#790000
0'
#795000
b10100 9
1#
1-
b0 ;
1'
#800000
0'
#805000
0#
0-
b10100 %
b10100 *
b10100 8
b1 ;
1'
#810000
0'
#815000
b10 ;
1'
#820000
0'
#825000
b11 ;
1'
#830000
0'
#835000
b10101 9
1#
1-
b0 ;
1'
#840000
0'
#845000
0#
0-
b10101 %
b10101 *
b10101 8
b1 ;
1'
#850000
0'
#855000
b10 ;
1'
#860000
0'
#865000
b11 ;
1'
#870000
0'
#875000
b10110 9
1#
1-
b0 ;
1'
#880000
0'
#885000
0#
0-
b10110 %
b10110 *
b10110 8
b1 ;
1'
#890000
0'
#895000
b10 ;
1'
#900000
0'
#905000
b11 ;
1'
#910000
0'
#915000
b10111 9
1#
1-
b0 ;
1'
#920000
0'
#925000
0#
0-
b10111 %
b10111 *
b10111 8
b1 ;
1'
#930000
0'
#935000
b10 ;
1'
#940000
0'
#945000
b11 ;
1'
#950000
0'
#955000
b11000 9
1#
1-
b0 ;
1'
#960000
0'
#965000
0#
0-
b11000 %
b11000 *
b11000 8
b1 ;
1'
#970000
0'
#975000
b10 ;
1'
#980000
0'
#985000
b11 ;
1'
#990000
0'
#995000
b11001 9
1#
1-
b0 ;
1'
#1000000
0'
#1005000
0#
0-
b11001 %
b11001 *
b11001 8
b1 ;
1'
#1010000
0'
#1015000
b10 ;
1'
#1020000
0'
#1025000
b11 ;
1'
#1030000
0'
#1035000
b11010 9
1#
1-
b0 ;
1'
#1040000
0'
#1045000
0#
0-
b11010 %
b11010 *
b11010 8
b1 ;
1'
#1050000
0'
#1055000
b10 ;
1'
#1060000
0'
#1065000
b11 ;
1'
#1070000
0'
#1075000
b11011 9
1#
1-
b0 ;
1'
#1080000
0'
#1085000
0#
0-
b11011 %
b11011 *
b11011 8
b1 ;
1'
#1090000
0'
#1095000
b10 ;
1'
#1100000
0'
#1105000
b11 ;
1'
#1110000
0'
#1115000
b11100 9
1#
1-
b0 ;
1'
#1120000
0'
#1125000
0#
0-
b11100 %
b11100 *
b11100 8
b1 ;
1'
#1130000
0'
#1135000
b10 ;
1'
#1140000
0'
#1145000
b11 ;
1'
#1150000
0'
#1155000
b11101 9
1#
1-
b0 ;
1'
#1160000
0'
#1165000
0#
0-
b11101 %
b11101 *
b11101 8
b1 ;
1'
#1170000
0'
#1175000
b10 ;
1'
#1180000
0'
#1185000
b11 ;
1'
#1190000
0'
#1195000
b11110 9
1#
1-
b0 ;
1'
#1200000
0'
#1205000
0#
0-
b11110 %
b11110 *
b11110 8
b1 ;
1'
#1210000
0'
#1215000
b10 ;
1'
#1220000
0'
#1225000
b11 ;
1'
#1230000
0'
#1235000
b11111 9
1#
1-
b0 ;
1'
#1240000
0'
#1245000
0#
0-
b11111 %
b11111 *
b11111 8
b1 ;
1'
#1250000
0'
#1255000
b10 ;
1'
#1260000
0'
#1265000
b11 ;
1'
#1270000
0'
#1275000
b100000 9
1#
1-
b0 ;
1'
#1280000
0'
#1285000
0#
0-
b100000 %
b100000 *
b100000 8
b1 ;
1'
#1290000
0'
#1295000
b10 ;
1'
#1300000
0'
#1305000
b11 ;
1'
#1310000
0'
#1315000
b100001 9
1#
1-
b0 ;
1'
#1320000
0'
#1325000
0#
0-
b100001 %
b100001 *
b100001 8
b1 ;
1'
#1330000
0'
#1335000
b10 ;
1'
#1340000
0'
#1345000
b11 ;
1'
#1350000
0'
#1355000
b100010 9
1#
1-
b0 ;
1'
#1360000
0'
#1365000
0#
0-
b100010 %
b100010 *
b100010 8
b1 ;
1'
#1370000
0'
#1375000
b10 ;
1'
#1380000
0'
#1385000
b11 ;
1'
#1390000
0'
#1395000
b100011 9
1#
1-
b0 ;
1'
#1400000
0'
#1405000
0#
0-
b100011 %
b100011 *
b100011 8
b1 ;
1'
#1410000
0'
#1415000
b10 ;
1'
#1420000
0'
#1425000
b11 ;
1'
#1430000
0'
#1435000
b100100 9
1#
1-
b0 ;
1'
#1440000
0'
#1445000
0#
0-
b100100 %
b100100 *
b100100 8
b1 ;
1'
#1450000
0'
#1455000
b10 ;
1'
#1460000
0'
#1465000
b11 ;
1'
#1470000
0'
#1475000
b100101 9
1#
1-
b0 ;
1'
#1480000
0'
#1485000
0#
0-
b100101 %
b100101 *
b100101 8
b1 ;
1'
#1490000
0'
#1495000
b10 ;
1'
#1500000
0'
#1505000
b11 ;
1'
#1510000
0'
#1515000
b100110 9
1#
1-
b0 ;
1'
#1520000
0'
#1525000
0#
0-
b100110 %
b100110 *
b100110 8
b1 ;
1'
#1530000
0'
#1535000
b10 ;
1'
#1540000
0'
#1545000
b11 ;
1'
#1550000
0'
#1555000
b100111 9
1#
1-
b0 ;
1'
#1560000
0'
#1565000
0#
0-
b100111 %
b100111 *
b100111 8
b1 ;
1'
#1570000
0'
#1575000
b10 ;
1'
#1580000
0'
#1585000
b11 ;
1'
#1590000
0'
#1595000
b101000 9
1#
1-
b0 ;
1'
#1600000
0'
#1605000
0#
0-
b101000 %
b101000 *
b101000 8
b1 ;
1'
#1610000
0'
#1615000
b10 ;
1'
#1620000
0'
#1625000
b11 ;
1'
#1630000
0'
#1635000
b101001 9
1#
1-
b0 ;
1'
#1640000
0'
#1645000
0#
0-
b101001 %
b101001 *
b101001 8
b1 ;
1'
#1650000
0'
#1655000
b10 ;
1'
#1660000
0'
#1665000
b11 ;
1'
#1670000
0'
#1675000
b101010 9
1#
1-
b0 ;
1'
#1680000
0'
#1685000
0#
0-
b101010 %
b101010 *
b101010 8
b1 ;
1'
#1690000
0'
#1695000
b10 ;
1'
#1700000
0'
#1705000
b11 ;
1'
#1710000
0'
#1715000
b101011 9
1#
1-
b0 ;
1'
#1720000
0'
#1725000
0#
0-
b101011 %
b101011 *
b101011 8
b1 ;
1'
#1730000
0'
#1735000
b10 ;
1'
#1740000
0'
#1745000
b11 ;
1'
#1750000
0'
#1755000
b101100 9
1#
1-
b0 ;
1'
#1760000
0'
#1765000
0#
0-
b101100 %
b101100 *
b101100 8
b1 ;
1'
#1770000
0'
#1775000
b10 ;
1'
#1780000
0'
#1785000
b11 ;
1'
#1790000
0'
#1795000
b101101 9
1#
1-
b0 ;
1'
#1800000
0'
#1805000
0#
0-
b101101 %
b101101 *
b101101 8
b1 ;
1'
#1810000
0'
#1815000
b10 ;
1'
#1820000
0'
#1825000
b11 ;
1'
#1830000
0'
#1835000
b101110 9
1#
1-
b0 ;
1'
#1840000
0'
#1845000
0#
0-
b101110 %
b101110 *
b101110 8
b1 ;
1'
#1850000
0'
#1855000
b10 ;
1'
#1860000
0'
#1865000
b11 ;
1'
#1870000
0'
#1875000
b101111 9
1#
1-
b0 ;
1'
#1880000
0'
#1885000
0#
0-
b101111 %
b101111 *
b101111 8
b1 ;
1'
#1890000
0'
#1895000
b10 ;
1'
#1900000
0'
#1905000
b11 ;
1'
#1910000
0'
#1915000
b110000 9
1#
1-
b0 ;
1'
#1920000
0'
#1925000
0#
0-
b110000 %
b110000 *
b110000 8
b1 ;
1'
#1930000
0'
#1935000
b10 ;
1'
#1940000
0'
#1945000
b11 ;
1'
#1950000
0'
#1955000
b110001 9
1#
1-
b0 ;
1'
#1960000
0'
#1965000
0#
0-
b110001 %
b110001 *
b110001 8
b1 ;
1'
#1970000
0'
#1975000
b10 ;
1'
#1980000
0'
#1985000
b11 ;
1'
#1990000
0'
#1995000
b110010 9
1#
1-
b0 ;
1'
#2000000
0'
#2005000
0#
0-
b110010 %
b110010 *
b110010 8
b1 ;
1'
#2010000
0'
#2015000
b10 ;
1'
#2020000
0'
#2025000
b11 ;
1'
#2030000
0'
#2035000
b110011 9
1#
1-
b0 ;
1'
#2040000
0'
#2045000
0#
0-
b110011 %
b110011 *
b110011 8
b1 ;
1'
#2050000
0'
#2055000
b10 ;
1'
#2060000
0'
#2065000
b11 ;
1'
#2070000
0'
#2075000
b110100 9
1#
1-
b0 ;
1'
#2080000
0'
#2085000
0#
0-
b110100 %
b110100 *
b110100 8
b1 ;
1'
#2090000
0'
#2095000
b10 ;
1'
#2100000
0'
#2105000
b11 ;
1'
#2110000
0'
#2115000
b110101 9
1#
1-
b0 ;
1'
#2120000
0'
#2125000
0#
0-
b110101 %
b110101 *
b110101 8
b1 ;
1'
#2130000
0'
#2135000
b10 ;
1'
#2140000
0'
#2145000
b11 ;
1'
#2150000
0'
#2155000
b110110 9
1#
1-
b0 ;
1'
#2160000
0'
#2165000
0#
0-
b110110 %
b110110 *
b110110 8
b1 ;
1'
#2170000
0'
#2175000
b10 ;
1'
#2180000
0'
#2185000
b11 ;
1'
#2190000
0'
#2195000
b110111 9
1#
1-
b0 ;
1'
#2200000
0'
#2205000
0#
0-
b110111 %
b110111 *
b110111 8
b1 ;
1'
#2210000
0'
#2215000
b10 ;
1'
#2220000
0'
#2225000
b11 ;
1'
#2230000
0'
#2235000
b111000 9
1#
1-
b0 ;
1'
#2240000
0'
#2245000
0#
0-
b111000 %
b111000 *
b111000 8
b1 ;
1'
#2250000
0'
#2255000
b10 ;
1'
#2260000
0'
#2265000
b11 ;
1'
#2270000
0'
#2275000
b111001 9
1#
1-
b0 ;
1'
#2280000
0'
#2285000
0#
0-
b111001 %
b111001 *
b111001 8
b1 ;
1'
#2290000
0'
#2295000
b10 ;
1'
#2300000
0'
#2305000
b11 ;
1'
#2310000
0'
#2315000
b111010 9
1#
1-
b0 ;
1'
#2320000
0'
#2325000
0#
0-
b111010 %
b111010 *
b111010 8
b1 ;
1'
#2330000
0'
#2335000
b10 ;
1'
#2340000
0'
#2345000
b11 ;
1'
#2350000
0'
#2355000
b111011 9
1#
1-
b0 ;
1'
#2360000
0'
#2365000
0#
0-
b111011 %
b111011 *
b111011 8
b1 ;
1'
#2370000
0'
#2375000
b10 ;
1'
#2380000
0'
#2385000
b11 ;
1'
#2390000
0'
#2395000
b111100 9
1#
1-
b0 ;
1'
#2400000
0'
#2405000
0#
0-
b111100 %
b111100 *
b111100 8
b1 ;
1'
#2410000
0'
#2415000
b10 ;
1'
#2420000
0'
#2425000
b11 ;
1'
#2430000
0'
#2435000
b111101 9
1#
1-
b0 ;
1'
#2440000
0'
#2445000
0#
0-
b111101 %
b111101 *
b111101 8
b1 ;
1'
#2450000
0'
#2455000
b10 ;
1'
#2460000
0'
#2465000
b11 ;
1'
#2470000
0'
#2475000
b111110 9
1#
1-
b0 ;
1'
#2480000
0'
#2485000
0#
0-
b111110 %
b111110 *
b111110 8
b1 ;
1'
#2490000
0'
#2495000
b10 ;
1'
#2500000
0'
#2505000
b11 ;
1'
#2510000
0'
#2515000
b111111 9
1#
1-
b0 ;
1'
#2520000
0'
#2525000
0#
0-
b111111 %
b111111 *
b111111 8
b1 ;
1'
#2530000
0'
#2535000
b10 ;
1'
#2540000
0'
#2545000
b11 ;
1'
#2550000
0'
#2555000
b1000000 9
1#
1-
b0 ;
1'
#2560000
0'
#2565000
0#
0-
b1000000 %
b1000000 *
b1000000 8
b1 ;
1'
#2570000
0'
#2575000
b10 ;
1'
#2580000
0'
#2585000
b11 ;
1'
#2590000
0'
#2595000
b1000001 9
1#
1-
b0 ;
1'
#2600000
0'
#2605000
0#
0-
b1000001 %
b1000001 *
b1000001 8
b1 ;
1'
#2610000
0'
#2615000
b10 ;
1'
#2620000
0'
#2625000
b11 ;
1'
#2630000
0'
#2635000
b1000010 9
1#
1-
b0 ;
1'
#2640000
0'
#2645000
0#
0-
b1000010 %
b1000010 *
b1000010 8
b1 ;
1'
#2650000
0'
#2655000
b10 ;
1'
#2660000
0'
#2665000
b11 ;
1'
#2670000
0'
#2675000
b1000011 9
1#
1-
b0 ;
1'
#2680000
0'
#2685000
0#
0-
b1000011 %
b1000011 *
b1000011 8
b1 ;
1'
#2690000
0'
#2695000
b10 ;
1'
#2700000
0'
#2705000
b11 ;
1'
#2710000
0'
#2715000
b1000100 9
1#
1-
b0 ;
1'
#2720000
0'
#2725000
0#
0-
b1000100 %
b1000100 *
b1000100 8
b1 ;
1'
#2730000
0'
#2735000
b10 ;
1'
#2740000
0'
#2745000
b11 ;
1'
#2750000
0'
#2755000
b1000101 9
1#
1-
b0 ;
1'
#2760000
0'
#2765000
0#
0-
b1000101 %
b1000101 *
b1000101 8
b1 ;
1'
#2770000
0'
#2775000
b10 ;
1'
#2780000
0'
#2785000
b11 ;
1'
#2790000
0'
#2795000
b1000110 9
1#
1-
b0 ;
1'
#2800000
0'
#2805000
0#
0-
b1000110 %
b1000110 *
b1000110 8
b1 ;
1'
#2810000
0'
#2815000
b10 ;
1'
#2820000
0'
#2825000
b11 ;
1'
#2830000
0'
#2835000
b1000111 9
1#
1-
b0 ;
1'
#2840000
0'
#2845000
0#
0-
b1000111 %
b1000111 *
b1000111 8
b1 ;
1'
#2850000
0'
#2855000
b10 ;
1'
#2860000
0'
#2865000
b11 ;
1'
#2870000
0'
#2875000
b1001000 9
1#
1-
b0 ;
1'
#2880000
0'
#2885000
0#
0-
b1001000 %
b1001000 *
b1001000 8
b1 ;
1'
#2890000
0'
#2895000
b10 ;
1'
#2900000
0'
#2905000
b11 ;
1'
#2910000
0'
#2915000
b1001001 9
1#
1-
b0 ;
1'
#2920000
0'
#2925000
0#
0-
b1001001 %
b1001001 *
b1001001 8
b1 ;
1'
#2930000
0'
#2935000
b10 ;
1'
#2940000
0'
#2945000
b11 ;
1'
#2950000
0'
#2955000
b1001010 9
1#
1-
b0 ;
1'
#2960000
0'
#2965000
0#
0-
b1001010 %
b1001010 *
b1001010 8
b1 ;
1'
#2970000
0'
#2975000
b10 ;
1'
#2980000
0'
#2985000
b11 ;
1'
#2990000
0'
#2995000
b1001011 9
1#
1-
b0 ;
1'
#3000000
0'
#3005000
0#
0-
b1001011 %
b1001011 *
b1001011 8
b1 ;
1'
#3010000
0'
#3015000
b10 ;
1'
#3020000
0'
#3025000
b11 ;
1'
#3030000
0'
#3035000
b1001100 9
1#
1-
b0 ;
1'
#3040000
0'
#3045000
0#
0-
b1001100 %
b1001100 *
b1001100 8
b1 ;
1'
#3050000
0'
#3055000
b10 ;
1'
#3060000
0'
#3065000
b11 ;
1'
#3070000
0'
#3075000
b1001101 9
1#
1-
b0 ;
1'
#3080000
0'
#3085000
0#
0-
b1001101 %
b1001101 *
b1001101 8
b1 ;
1'
#3090000
0'
#3095000
b10 ;
1'
#3100000
0'
#3105000
b11 ;
1'
#3110000
0'
#3115000
b1001110 9
1#
1-
b0 ;
1'
#3120000
0'
#3125000
0#
0-
b1001110 %
b1001110 *
b1001110 8
b1 ;
1'
#3130000
0'
#3135000
b10 ;
1'
#3140000
0'
#3145000
b11 ;
1'
#3150000
0'
#3155000
b1001111 9
1#
1-
b0 ;
1'
#3160000
0'
#3165000
0#
0-
b1001111 %
b1001111 *
b1001111 8
b1 ;
1'
#3170000
0'
#3175000
b10 ;
1'
#3180000
0'
#3185000
b11 ;
1'
#3190000
0'
#3195000
b1010000 9
1#
1-
b0 ;
1'
#3200000
0'
#3205000
0#
0-
b1010000 %
b1010000 *
b1010000 8
b1 ;
1'
#3210000
0'
#3215000
b10 ;
1'
#3220000
0'
#3225000
b11 ;
1'
#3230000
0'
#3235000
b1010001 9
1#
1-
b0 ;
1'
#3240000
0'
#3245000
0#
0-
b1010001 %
b1010001 *
b1010001 8
b1 ;
1'
#3250000
0'
#3255000
b10 ;
1'
#3260000
0'
#3265000
b11 ;
1'
#3270000
0'
#3275000
b1010010 9
1#
1-
b0 ;
1'
#3280000
0'
#3285000
0#
0-
b1010010 %
b1010010 *
b1010010 8
b1 ;
1'
#3290000
0'
#3295000
b10 ;
1'
#3300000
0'
#3305000
b11 ;
1'
#3310000
0'
#3315000
b1010011 9
1#
1-
b0 ;
1'
#3320000
0'
#3325000
0#
0-
b1010011 %
b1010011 *
b1010011 8
b1 ;
1'
#3330000
0'
#3335000
b10 ;
1'
#3340000
0'
#3345000
b11 ;
1'
#3350000
0'
#3355000
b1010100 9
1#
1-
b0 ;
1'
#3360000
0'
#3365000
0#
0-
b1010100 %
b1010100 *
b1010100 8
b1 ;
1'
#3370000
0'
#3375000
b10 ;
1'
#3380000
0'
#3385000
b11 ;
1'
#3390000
0'
#3395000
b1010101 9
1#
1-
b0 ;
1'
#3400000
0'
#3405000
0#
0-
b1010101 %
b1010101 *
b1010101 8
b1 ;
1'
#3410000
0'
#3415000
b10 ;
1'
#3420000
0'
#3425000
b11 ;
1'
#3430000
0'
#3435000
b1010110 9
1#
1-
b0 ;
1'
#3440000
0'
#3445000
0#
0-
b1010110 %
b1010110 *
b1010110 8
b1 ;
1'
#3450000
0'
#3455000
b10 ;
1'
#3460000
0'
#3465000
b11 ;
1'
#3470000
0'
#3475000
b1010111 9
1#
1-
b0 ;
1'
#3480000
0'
#3485000
0#
0-
b1010111 %
b1010111 *
b1010111 8
b1 ;
1'
