VivadoProjects/rtl/VGA_Sync_Handler.v
// Based on documentation fromDavid J. Marion in reference to:
// 
// Chu, Pong P.
// Wiley, 2008
// "FPGA Prototyping by Verilog Examples: Xilinx Spartan-3 Version" 
//
// Based on an FPGA with 100MHz clock
//
// VGA Specs:
// 640x480 pixel resolution at 60 Hz
// Based on VGA standards, we need "extra" resolution outside visible area (porches). This gives:
// 800 pixels/line and 525 lines/screen @60Hz ==> 800*525*60 = ~25M pixels/second
//
// This means we will need a 25 MHz signal to run the VGA protocol (need to generate horizontal sync, vertical sync, 
// pixel signal, and a display on signal)


module vga_handler(
    i_clock,
    i_reset,
    o_display_on,
    o_hsync,
    o_vsync,
    o_pixel_clock,
    o_h_spot,
    o_v_spot
);

input i_clock;          //100 MHz from Artix-7
input i_reset;          // to reset system
output o_display_on;     // this is high when we are rastering within the visible display area (640x480 area)
output o_hsync;         // horizontal sync (signals when a line is finished)
output o_vsync;         // vertical sync (signals when last line on screen is finished)
output o_pixel_clock;   // 25MHz signal for controlling pixel/second display rate
output [9:0] o_h_spot;  // counter for keeping track of what pixel we are on horizontally      
output [9:0] o_v_spot;  // counter for keeping track of what pixel we are on vertically

// We now will lay out the values we will use for sectioning the total pixel area into the visible, and 
// various non-visible sections as described by the VGA standard (Included in this folder is a schematic from
// electronics stack exchange that shows the various areas outlined in the VGA standards)

//horizontal
parameter horz_dis_area = 640;      //width of horizontal display area in pixels
parameter horz_front = 48;          // horizontal front porch width in pixels
parameter horz_back = 16;           // horizontal back porch width in pixels
parameter horz_retrace = 96;        // horizontal retrace area width in pixels
parameter horz_max = (horz_dis_area + horz_front + horz_back + horz_retrace) - 1; //max number for horz_counter
                                                                                  // horz_max = 799 pixels
//vertical (all variables descriptions are same, just for vertical)
parameter vert_dis_area = 480;      
parameter vert_front = 10;          
parameter vert_back = 33;           
parameter vert_retrace = 2;        
parameter vert_max = (vert_dis_area + vert_front + vert_back + vert_retrace) - 1; //max number for horz_counter
                                                                                  // vert_max = 524 pixels

// We now will generate the 25MHz signal we will use to drive our pixel tick and increment our counters with:
      
reg [1:0] quarter_counter = 2'b00; //2 bit number that wraps every 4 increments 00,01,10,11 --> 00, . . . 

always @ (posedge i_clock)
    begin
    if(i_reset)
        quarter_counter <= 0;
    else
        quarter_counter <= quarter_counter + 1; //increment quarter counter
    end

//essentially, because quarter counter only has 2 values (2-bit binary number) we can check for one of these 
//values to be true to give us a high signal (logical true) 1/4 of the time. Therefore if we are incrementing
//quarter_counter at a rate of 100MHz with this logic, we will get a 100MHz/4 or 25MHz signal!
wire c_25MHz = (quarter_counter == 0) ? 1 : 0; //clock output (wire so that it globally updates immediately -- not registered)
assign o_pixel_clock = c_25MHz; 

// We will now move on to the generation of the syncing and pixel location signals:
// We make two temporary registers for each sync signal to cut down on any metastability issues and visual bugs:

// counters for pixel locations (two for each to ripple for stability):
reg [9:0] h_count_pre;
reg [9:0] h_count_post;
reg [9:0] v_count_pre;
reg [9:0] v_count_post;

//  syncing signal (two for each to ripple for stability):
wire h_sync_pre;
wire v_sync_pre;
reg h_sync_post;
reg v_sync_post;

//Ripple the registers (both counters and sync signals)
always @ (posedge i_clock)
    if(i_reset)
    begin
        h_count_pre <= 0;
        v_count_pre <= 0;
        h_sync_post <= 1'b0;
        v_sync_post <= 1'b0;
    end
    else begin
        h_count_post <= h_count_pre;
        v_count_post <= v_count_pre;
        h_sync_post <= h_sync_pre;
        v_sync_post <= v_sync_pre;
    end

// Now we can actually do the counter logic to generate the signals we need:
//
// For Horizontal pixel count:
always @ (posedge i_clock)       //running on the 100MHz clock to not cause clock domain issues
    begin
    if(i_reset) begin
        h_count_pre <= 0;
    end
    else if(c_25MHz)begin
            if(h_count_post == horz_max)                //This is when we reach the end of a line!
                h_count_pre <= 0;                       
            else
                h_count_pre <= h_count_post +1;         // If not at the end of line, just increase count
            end
    end

// For vertical counter:

always @ (posedge i_clock)
    begin
        if(i_reset)begin
            v_count_pre <= 0;
        end
        else if(c_25MHz) begin
                if(h_count_post == horz_max)
                begin
                    if(v_count_post == vert_max)
                        v_count_pre <= 0;
                    else
                        v_count_pre <= v_count_post + 1;
                end
        end
    end

// We can now generate the sync pulses (we want these to be high during retrace and low everywhere else)

// horizontal sync pulse:

// we make this low when we are both:
// 1) Past the visible display area and porch
// 2) Before the end of the retrace width
assign h_sync_pre = (h_count_post >= (horz_dis_area + horz_back) && h_count_post <= (horz_dis_area + horz_back + horz_retrace - 1));

// We do the same for the vertical sync pulse:

assign v_sync_pre = (v_count_post >= (vert_dis_area + vert_back) && v_count_post <= (vert_dis_area + vert_back + vert_retrace - 1));

// And now we set the display_on signal high when we are both:
// 1) within the horizontal display area
// 2) within the vertical display area

assign o_display_on = ((h_count_post < horz_dis_area) && (v_count_post < vert_dis_area)); //1 when in dis. area 0 outside of it

//Now we just assign all of our outputs from the rippled values:

assign o_hsync = h_sync_post;
assign o_vsync = v_sync_post;
assign o_h_spot = h_count_post;
assign o_v_spot = v_count_post;
assign o_pixel_clock = c_25MHz;

endmodule

VGA_Sync_HandlerTB.v
`timescale 1ns / 1ps
`include "VGA_Sync_Handler.v"

module  VGA_Sync_HandlerTB;

//define signals from test bench

reg tb_clock = 1'b0;
reg tb_reset = 1'b1;

wire tb_display_on;
wire tb_hsync;
wire tb_vsync;
wire tb_pixel_clock;
wire [9:0] tb_h_spot;
wire [9:0] tb_v_spot;

vga_handler UUT
(
    .i_clock(tb_clock),
    .i_reset(tb_reset),
    .o_display_on(tb_display_on),
    .o_hsync(tb_hsync),
    .o_vsync(tb_vsync),
    .o_pixel_clock(tb_pixel_clock),
    .o_h_spot(tb_h_spot),
    .o_v_spot(tb_v_spot)
);

initial begin
    $dumpfile("VGA_Sync_HandlerTB.vcd"); //dump file name
    $dumpvars(0, VGA_Sync_HandlerTB);  //dumps all signals in test bench
end

// Here we are generating a 100kHz clock signal. We can do this by using # to pause for the
// correct number of loops so that our period we are using to define tb_clock is equal to the period
// of a 100kHz clock --> 100kHz = 1/100,000 seconds = 0.00001 seconds or 10us. it takes 2 toggles for 
//a complete period so we divide the waitcount by 2. This means we need to wait for 10 us so we use #5000

always #5 tb_clock <= !tb_clock;  //toggle the value from 0 -> 1 -> 0 -> ... makes square wave => Clock signal!

// run code that we run only once to set up test environment. This is why we use "initial"
initial begin

    $display("Testing VGA_Handler");

    tb_reset <= 1'b0;
    #200000
    tb_reset <= 1'b1;

    $display("Test Complete");  //to make sure test finishes!
    $finish;

end

endmodule

VGA_Pong/VGA_Pong.sim/sim_1/behav/xsim/VGA_Sync_HandlerTB.vcd
$date
   Sat May 31 22:08:24 2025
$end

$version
  2024.2.0
  $dumpfile ("VGA_Sync_HandlerTB.vcd") 
$end

$timescale
  1ps
$end

$scope module VGA_Sync_HandlerTB $end
$var reg 1 ! tb_clock $end
$var reg 1 " tb_reset $end
$var wire 1 # tb_display_on $end
$var wire 1 $ tb_hsync $end
$var wire 1 % tb_vsync $end
$var wire 1 & tb_pixel_clock $end
$var wire 10 ' tb_h_spot [9:0] $end
$var wire 10 ( tb_v_spot [9:0] $end
$scope module UUT $end
$var wire 1 ) i_clock $end
$var wire 1 * i_reset $end
$var wire 1 # o_display_on $end
$var wire 1 $ o_hsync $end
$var wire 1 % o_vsync $end
$var wire 1 & o_pixel_clock $end
$var wire 10 ' o_h_spot [9:0] $end
$var wire 10 ( o_v_spot [9:0] $end
$var wire 1 + c_25MHz $end
$var reg 2 , quarter_counter [1:0] $end
$var reg 10 - h_count_pre [9:0] $end
$var reg 10 . h_count_post [9:0] $end
$var reg 10 / v_count_pre [9:0] $end
$var reg 10 0 v_count_post [9:0] $end
$var wire 1 1 h_sync_pre $end
$var wire 1 2 v_sync_pre $end
$var reg 1 3 h_sync_post $end
$var reg 1 4 v_sync_post $end
$upscope $end
$upscope $end
$enddefinitions $end

#0
$dumpvars
0!
0"
x#
0$
0%
1&
bx '
bx (
0)
0*
1+
b0 ,
b0 -
bx .
b0 /
bx 0
x1
x2
03
04
$end

#5000
1!
1#
x$
x%
0&
b0 '
b0 (
1)
0+
b1 ,
b0 .
b0 0
01
02
x3
x4

#10000
0!
0)

#15000
1!
0$
0%
1)
b10 ,
03
04

#20000
0!
0)

#25000
1!
1)
b11 ,

#30000
0!
0)

#35000
1!
1&
1)
1+
b0 ,
b1 -

#40000
0!
0)

#45000
1!
0&
b1 '
1)
0+
b1 ,
b1 .

#50000
0!
0)

#55000
1!
1)
b10 ,

#60000
0!
0)

#65000
1!
1)
b11 ,

#70000
0!
0)

#75000
1!
1&
1)
1+
b0 ,
b10 -

#80000
0!
0)

#85000
1!
0&
b10 '
1)
0+
b1 ,
b10 .

#90000
0!
0)

#95000
1!
1)
b10 ,

#100000
0!
0)

#105000
1!
1)
b11 ,

#110000
0!
0)

#115000
1!
1&
1)
1+
b0 ,
b11 -

#120000
0!
0)

#125000
1!
0&
b11 '
1)
0+
b1 ,
b11 .

#130000
0!
0)

#135000
1!
1)
b10 ,

#140000
0!
0)

#145000
1!
1)
b11 ,

#150000
0!
0)

#155000
1!
1&
1)
1+
b0 ,
b100 -

#160000
0!
0)

#165000
1!
0&
b100 '
1)
0+
b1 ,
b100 .

#170000
0!
0)

#175000
1!
1)
b10 ,

#180000
0!
0)

#185000
1!
1)
b11 ,

#190000
0!
0)

#195000
1!
1&
1)
1+
b0 ,
b101 -

#200000
0!
0)

#205000
1!
0&
b101 '
1)
0+
b1 ,
b101 .

#210000
0!
0)

#215000
1!
1)
b10 ,

#220000
0!
0)

#225000
1!
1)
b11 ,

#230000
0!
0)

#235000
1!
1&
1)
1+
b0 ,
b110 -

#240000
0!
0)

#245000
1!
0&
b110 '
1)
0+
b1 ,
b110 .

#250000
0!
0)

#255000
1!
1)
b10 ,

#260000
0!
0)

#265000
1!
1)
b11 ,

#270000
0!
0)

#275000
1!
1&
1)
1+
b0 ,
b111 -

#280000
0!
0)

#285000
1!
0&
b111 '
1)
0+
b1 ,
b111 .

#290000
0!
0)

#295000
1!
1)
b10 ,

#300000
0!
0)

#305000
1!
1)
b11 ,

#310000
0!
0)

#315000
1!
1&
1)
1+
b0 ,
b1000 -

#320000
0!
0)

#325000
1!
0&
b1000 '
1)
0+
b1 ,
b1000 .

#330000
0!
0)

#335000
1!
1)
b10 ,

#340000
0!
0)

#345000
1!
1)
b11 ,

#350000
0!
0)

#355000
1!
1&
1)
1+
b0 ,
b1001 -

#360000
0!
0)

#365000
1!
0&
b1001 '
1)
0+
b1 ,
b1001 .

#370000
0!
0)

#375000
1!
1)
b10 ,

#380000
0!
0)

#385000
1!
1)
b11 ,

#390000
0!
0)

#395000
1!
1&
1)
1+
b0 ,
b1010 -

#400000
0!
0)

#405000
1!
0&
b1010 '
1)
0+
b1 ,
b1010 .

#410000
0!
0)

#415000
1!
1)
b10 ,

#420000
0!
0)

#425000
1!
1)
b11 ,

#430000
0!
0)

#435000
1!
1&
1)
1+
b0 ,
b1011 -

#440000
0!
0)

#445000
1!
0&
b1011 '
1)
0+
b1 ,
b1011 .

#450000
0!
0)

#455000
1!
1)
b10 ,

#460000
0!
0)

#465000
1!
1)
b11 ,

#470000
0!
0)

#475000
1!
1&
1)
1+
b0 ,
b1100 -

#480000
0!
0)

#485000
1!
0&
b1100 '
1)
0+
b1 ,
b1100 .

#490000
0!
0)

#495000
1!
1)
b10 ,

#500000
0!
0)

#505000
1!
1)
b11 ,

#510000
0!
0)

#515000
1!
1&
1)
1+
b0 ,
b1101 -

#520000
0!
0)

#525000
1!
0&
b1101 '
1)
0+
b1 ,
b1101 .

#530000
0!
0)

#535000
1!
1)
b10 ,

#540000
0!
0)

#545000
1!
1)
b11 ,

#550000
0!
0)

#555000
1!
1&
1)
1+
b0 ,
b1110 -

#560000
0!
0)

#565000
1!
0&
b1110 '
1)
0+
b1 ,
b1110 .

#570000
0!
0)

#575000
1!
1)
b10 ,

#580000
0!
0)

#585000
1!
1)
b11 ,

#590000
0!
0)

#595000
1!
1&
1)
1+
b0 ,
b1111 -

#600000
0!
0)

#605000
1!
0&
b1111 '
1)
0+
b1 ,
b1111 .

#610000
0!
0)

#615000
1!
1)
b10 ,

#620000
0!
0)

#625000
1!
1)
b11 ,

#630000
0!
0)

#635000
1!
1&
1)
1+
b0 ,
b10000 -

#640000
0!
0)

#645000
1!
0&
b10000 '
1)
0+
b1 ,
b10000 .

#650000
0!
0)

#655000
1!
1)
b10 ,

#660000
0!
0)

#665000
1!
1)
b11 ,

#670000
0!
0)

#675000
1!
1&
1)
1+
b0 ,
b10001 -

#680000
0!
0)

#685000
1!
0&
b10001 '
1)
0+
b1 ,
b10001 .

#690000
0!
0)

#695000
1!
1)
b10 ,

#700000
0!
0)

#705000
1!
1)
b11 ,

#710000
0!
0)

#715000
1!
1&
1)
1+
b0 ,
b10010 -

#720000
0!
0)

#725000
1!
0&
b10010 '
1)
0+
b1 ,
b10010 .

#730000
0!
0)

#735000
1!
1)
b10 ,

#740000
0!
0)

#745000
1!
1)
b11 ,

#750000
0!
0)

#755000
1!
1&
1)
1+
b0 ,
b10011 -

#760000
0!
0)

#765000
1!
0&
b10011 '
1)
0+
b1 ,
b10011 .

#770000
0!
0)

#775000
1!
1)
b10 ,

#780000
0!
0)

#785000
1!
1)
b11 ,

#790000
0!
0)

#795000
1!
1&
1)
1+
b0 ,
b10100 -

#800000
0!
0)

#805000
1!
0&
b10100 '
1)
0+
b1 ,
b10100 .

#810000
0!
0)

#815000
1!
1)
b10 ,

#820000
0!
0)

#825000
1!
1)
b11 ,

#830000
0!
0)

#835000
1!
1&
1)
1+
b0 ,
b10101 -

#840000
0!
0)

#845000
1!
0&
b10101 '
1)
0+
b1 ,
b10101 .

#850000
0!
0)

#855000
1!
1)
b10 ,

#860000
0!
0)

#865000
1!
1)
b11 ,

#870000
0!
0)

#875000
1!
1&
1)
1+
b0 ,
b10110 -

#880000
0!
0)

#885000
1!
0&
b10110 '
1)
0+
b1 ,
b10110 .

#890000
0!
0)

#895000
1!
1)
b10 ,

#900000
0!
0)

#905000
1!
1)
b11 ,

#910000
0!
0)

#915000
1!
1&
1)
1+
b0 ,
b10111 -

#920000
0!
0)

#925000
1!
0&
b10111 '
1)
0+
b1 ,
b10111 .

#930000
0!
0)

#935000
1!
1)
b10 ,

#940000
0!
0)

#945000
1!
1)
b11 ,

#950000
0!
0)

#955000
1!
1&
1)
1+
b0 ,
b11000 -

#960000
0!
0)

#965000
1!
0&
b11000 '
1)
0+
b1 ,
b11000 .

#970000
0!
0)

#975000
1!
1)
b10 ,

#980000
0!
0)

#985000
1!
1)
b11 ,

#990000
0!
0)

#995000
1!
1&
1)
1+
b0 ,
b11001 -

